loica/__init__.py
loica/assay.py
loica/colony.py
loica/geneproduct.py
loica/genetic_network.py
loica/metabolism.py
loica/sample.py
loica/supplement.py
loica/util.py
loica/operators/__init__.py
loica/operators/hill1.py
loica/operators/hill2.py
loica/operators/operator.py
loica/operators/receiver.py
loica/operators/source.py
loica/operators/sum.py
loica-1.0.6.dist-info/LICENSE
loica-1.0.6.dist-info/METADATA
loica-1.0.6.dist-info/WHEEL
loica-1.0.6.dist-info/top_level.txt
loica-1.0.6.dist-info/RECORD
