Metadata-Version: 2.1
Name: loica
Version: 1.0.6
Summary: LOICA: Logical Operators for Integrated Cell Algorithms
Author-email: Gonzalo Vidal <g.a.vidal-pena2@ncl.ac.uk>, Timothy Rudge <tim.rudge@ncl.ac.uk>
Maintainer-email: Gonzalo Vidal <g.a.vidal-pena2@ncl.ac.uk>
License: MIT License
Project-URL: Homepage, https://github.com/RudgeLab/LOICA
Project-URL: Bug Tracker, https://github.com/RudgeLab/LOICA/issues
Keywords: loica,genetic,GDA,design,synthetic biology
Classifier: Programming Language :: Python :: 3
Classifier: License :: OSI Approved :: MIT License
Classifier: Operating System :: OS Independent
Requires-Python: >=3.7
License-File: LICENSE
Requires-Dist: numpy
Requires-Dist: scipy
Requires-Dist: networkx
Requires-Dist: pandas
Requires-Dist: sbol3
Requires-Dist: tyto
Requires-Dist: tdqm
Provides-Extra: test
Requires-Dist: pytest (<5.0.0) ; extra == 'test'
Requires-Dist: pytest-cov[all] ; extra == 'test'
